mkl_random/__init__.py
mkl_random/_init_helper.py
mkl_random/_version.py
mkl_random/mklrand.cp312-win_amd64.pyd
mkl_random/mklrand.pyx
mkl_random/src/mkl_distributions.cpp
mkl_random/src/randomkit.cpp
mkl_random/tests/__init__.py
mkl_random/tests/test_random.py
mkl_random/tests/test_regression.py
mkl_random-1.3.1.dist-info/licenses/LICENSE.txt
mkl_random-1.3.1.dist-info/METADATA
mkl_random-1.3.1.dist-info/WHEEL
mkl_random-1.3.1.dist-info/top_level.txt
mkl_random-1.3.1.dist-info/RECORD
