Metadata-Version: 2.4
Name: mkl_random
Version: 1.3.1
Summary: NumPy-based Python interface to Intel (R) MKL Random Number Generation functionality
Author-email: Intel Corporation <scripting@intel.com>
License-Expression: BSD-3-Clause
Project-URL: Download, http://github.com/IntelPython/mkl_random
Project-URL: Homepage, http://github.com/IntelPython/mkl_random
Keywords: MKL,VSL,true randomness,pseudorandomness,Philox,MT-19937,SFMT-19937,MT-2203,ARS-5,R-250,MCG-31
Classifier: Development Status :: 5 - Production/Stable
Classifier: Intended Audience :: Science/Research
Classifier: Intended Audience :: Developers
Classifier: Programming Language :: C
Classifier: Programming Language :: Python
Classifier: Programming Language :: Python :: 3
Classifier: Programming Language :: Python :: 3.9
Classifier: Programming Language :: Python :: 3.10
Classifier: Programming Language :: Python :: 3.11
Classifier: Programming Language :: Python :: 3.12
Classifier: Programming Language :: Python :: 3.13
Classifier: Programming Language :: Python :: 3.14
Classifier: Programming Language :: Python :: Implementation :: CPython
Classifier: Topic :: Software Development
Classifier: Topic :: Scientific/Engineering
Classifier: Operating System :: Microsoft :: Windows
Classifier: Operating System :: POSIX
Classifier: Operating System :: Unix
Requires-Python: <3.15,>=3.9
License-File: LICENSE.txt
Provides-Extra: test
Dynamic: license-file
Requires-Dist: mkl >=2025.3,<2026.0a0
Requires-Dist: numpy >=2.3,<3.0a0
